itb/__init__.py
itb/collection.py
itb/color.py
itb/consts.py
itb/file.py
itb/img.py
itb/vis.py
itb-0.1.1.dist-info/LICENSE
itb-0.1.1.dist-info/METADATA
itb-0.1.1.dist-info/WHEEL
itb-0.1.1.dist-info/top_level.txt
itb-0.1.1.dist-info/RECORD
