Metadata-Version: 2.1
Name: itb
Version: 0.1.1
Summary: Toolbox library for rapid prototyping of computer vision projects.
Author-email: Mateusz Choiński <mateusz.choinski100@gmail.com>
License: MIT License
Project-URL: Homepage, https://github.com/grafiszti/itb
Keywords: images,toolbox,computer vision,opencv,matplotlib,jupyter
Classifier: License :: OSI Approved :: MIT License
Classifier: Programming Language :: Python
Classifier: Programming Language :: Python :: 3
Requires-Python: >=3.10
License-File: LICENSE
Requires-Dist: matplotlib>=3.8.2
Requires-Dist: opencv-python>=4.8.1.78
Requires-Dist: pandas>=2.1.3
Requires-Dist: requests==2.32.3
Provides-Extra: dev
Requires-Dist: black==24.10.0; extra == "dev"
Requires-Dist: build==1.2.2.post1; extra == "dev"
Requires-Dist: flake8-pyproject==1.2.3; extra == "dev"
Requires-Dist: isort==5.13.2; extra == "dev"
Requires-Dist: jupyter==1.1.1; extra == "dev"
Requires-Dist: pytest==8.3.3; extra == "dev"
Requires-Dist: pytest-cov==5.0.0; extra == "dev"
Requires-Dist: setuptools==75.2.0; extra == "dev"
Requires-Dist: twine==5.1.1; extra == "dev"
Requires-Dist: virtualenv==20.27.0; extra == "dev"
